domainname/__init__.py
domainname/main.py
domainname-0.0.3.dist-info/METADATA
domainname-0.0.3.dist-info/WHEEL
domainname-0.0.3.dist-info/entry_points.txt
domainname-0.0.3.dist-info/RECORD
