Metadata-Version: 2.4
Name: domainname
Version: 0.0.3
Summary: Check domain name availability via CLI. Supports patterns for checking in batches.
Project-URL: homepage, https://github.com/albertas/domainname
Author-email: Albertas Gimbutas <albertasgim@gmail.com>
Classifier: Development Status :: 3 - Alpha
Classifier: License :: OSI Approved :: GNU Affero General Public License v3
Classifier: Natural Language :: English
Classifier: Operating System :: OS Independent
Classifier: Programming Language :: Python
Classifier: Programming Language :: Python :: 3.11
Requires-Python: >=3.11
Requires-Dist: python-whois==0.9.4
Provides-Extra: test
Requires-Dist: deadcode; extra == 'test'
Requires-Dist: hatch; extra == 'test'
Requires-Dist: mypy; extra == 'test'
Requires-Dist: pip-audit; extra == 'test'
Requires-Dist: pytest; extra == 'test'
Requires-Dist: pytest-cov; extra == 'test'
Requires-Dist: ruff; extra == 'test'
